{
  "33441": [
    1712,
    1713,
    1716,
    1714,
    1715
  ],
  "33768": [
    1722,
    1723
  ],
  "33775": [
    1742
  ],
  "33798": [
    1717,
    1733
  ],
  "33799": [
    1732,
    1737
  ],
  "33800": [
    1718
  ],
  "33801": [
    1728
  ],
  "33802": [
    1740
  ],
  "33803": [
    1731,
    1741
  ],
  "33804": [
    1719
  ],
  "33805": [
    1727
  ],
  "33806": [
    1736
  ],
  "33807": [
    1725
  ],
  "33808": [
    1735
  ],
  "33809": [
    1724
  ],
  "33810": [
    1730,
    1739
  ]
}