{
  "1": {
    "DEX": "-1",
    "Hp": 0,
    "ID": 1,
    "INT": 3,
    "MND": "-1",
    "Mp": 0,
    "Name": "Midlander",
    "Name_de": "Wiesländer",
    "Name_en": "Midlander",
    "Name_fr": "Hyurois",
    "Name_ja": "ミッドランダー ",
    "PIE": 0,
    "STR": 2,
    "VIT": 0
  },
  "2": {
    "DEX": 0,
    "Hp": 0,
    "ID": 2,
    "INT": "-2",
    "MND": 0,
    "Mp": 0,
    "Name": "Highlander",
    "Name_de": "Hochländer",
    "Name_en": "Highlander",
    "Name_fr": "Hyurgoth",
    "Name_ja": "ハイランダー",
    "PIE": 0,
    "STR": 3,
    "VIT": 2
  },
  "3": {
    "DEX": 3,
    "Hp": 0,
    "ID": 3,
    "INT": 2,
    "MND": "-1",
    "Mp": 0,
    "Name": "Wildwood",
    "Name_de": "Erlschatten",
    "Name_en": "Wildwood",
    "Name_fr": "Sylvestre",
    "Name_ja": "フォレスター",
    "PIE": 0,
    "STR": 0,
    "VIT": "-1"
  },
  "4": {
    "DEX": 0,
    "Hp": 0,
    "ID": 4,
    "INT": 3,
    "MND": 1,
    "Mp": 0,
    "Name": "Duskwight",
    "Name_de": "Dunkelalb",
    "Name_en": "Duskwight",
    "Name_fr": "Crépusculaire",
    "Name_ja": "シェーダー",
    "PIE": 0,
    "STR": 0,
    "VIT": "-1"
  },
  "5": {
    "DEX": 3,
    "Hp": 0,
    "ID": 5,
    "INT": 2,
    "MND": 0,
    "Mp": 0,
    "Name": "Plainsfolk",
    "Name_de": "Halmling",
    "Name_en": "Plainsfolk",
    "Name_fr": "Peuple des Plaines",
    "Name_ja": "プレーンフォーク",
    "PIE": 0,
    "STR": "-1",
    "VIT": "-1"
  },
  "6": {
    "DEX": 1,
    "Hp": 0,
    "ID": 6,
    "INT": 2,
    "MND": 3,
    "Mp": 0,
    "Name": "Dunesfolk",
    "Name_de": "Sandling",
    "Name_en": "Dunesfolk",
    "Name_fr": "Peuple des Dunes",
    "Name_ja": "デューンフォーク",
    "PIE": 0,
    "STR": "-1",
    "VIT": "-2"
  },
  "7": {
    "DEX": 3,
    "Hp": 0,
    "ID": 7,
    "INT": "-1",
    "MND": "-1",
    "Mp": 0,
    "Name": "Seeker of the Sun",
    "Name_de": "Goldtatze",
    "Name_en": "Seeker of the Sun",
    "Name_fr": "Tribu du Soleil",
    "Name_ja": "サンシーカー",
    "PIE": 0,
    "STR": 2,
    "VIT": 0
  },
  "8": {
    "DEX": 2,
    "Hp": 0,
    "ID": 8,
    "INT": 1,
    "MND": 3,
    "Mp": 0,
    "Name": "Keeper of the Moon",
    "Name_de": "Mondstreuner",
    "Name_en": "Keeper of the Moon",
    "Name_fr": "Tribu de la Lune",
    "Name_ja": "ムーンキーパー",
    "PIE": 0,
    "STR": "-1",
    "VIT": "-2"
  },
  "9": {
    "DEX": "-1",
    "Hp": 0,
    "ID": 9,
    "INT": "-2",
    "MND": 1,
    "Mp": 0,
    "Name": "Sea Wolf",
    "Name_de": "Seewolf",
    "Name_en": "Sea Wolf",
    "Name_fr": "Clan de la Mer",
    "Name_ja": "ゼーヴォルフ",
    "PIE": 0,
    "STR": 2,
    "VIT": 3
  },
  "10": {
    "DEX": "-2",
    "Hp": 0,
    "ID": 10,
    "INT": 0,
    "MND": 2,
    "Mp": 0,
    "Name": "Hellsguard",
    "Name_de": "Lohengarde",
    "Name_en": "Hellsguard",
    "Name_fr": "Clan du Feu",
    "Name_ja": "ローエンガルデ",
    "PIE": 0,
    "STR": 0,
    "VIT": 3
  },
  "11": {
    "DEX": 2,
    "Hp": 0,
    "ID": 11,
    "INT": 0,
    "MND": 3,
    "Mp": 0,
    "Name": "Raen",
    "Name_de": "Raen",
    "Name_en": "Raen",
    "Name_fr": "Raen",
    "Name_ja": "アウラ・レン",
    "PIE": 0,
    "STR": "-1",
    "VIT": "-1"
  },
  "12": {
    "DEX": 0,
    "Hp": 0,
    "ID": 12,
    "INT": 0,
    "MND": "-2",
    "Mp": 0,
    "Name": "Xaela",
    "Name_de": "Xaela",
    "Name_en": "Xaela",
    "Name_fr": "Xaela",
    "Name_ja": "アウラ・ゼラ",
    "PIE": 0,
    "STR": 3,
    "VIT": 2
  },
  "13": {
    "DEX": "-3",
    "Hp": 0,
    "ID": 13,
    "INT": "-3",
    "MND": 3,
    "Mp": 0,
    "Name": "Helions",
    "Name_de": "Helion",
    "Name_en": "Helions",
    "Name_fr": "Hélion",
    "Name_ja": "ヘリオン",
    "PIE": 0,
    "STR": 3,
    "VIT": 3
  },
  "14": {
    "DEX": "-3",
    "Hp": 0,
    "ID": 14,
    "INT": "-3",
    "MND": 3,
    "Mp": 0,
    "Name": "The Lost",
    "Name_de": "Losgesagter",
    "Name_en": "The Lost",
    "Name_fr": "Éloigné",
    "Name_ja": "ロスト",
    "PIE": 0,
    "STR": 3,
    "VIT": 3
  },
  "15": {
    "DEX": 3,
    "Hp": 0,
    "ID": 15,
    "INT": 1,
    "MND": 1,
    "Mp": 0,
    "Name": "Rava",
    "Name_de": "Rava",
    "Name_en": "Rava",
    "Name_fr": "Rava",
    "Name_ja": "ラヴァ・ヴィエラ",
    "PIE": 0,
    "STR": 0,
    "VIT": "-2"
  },
  "16": {
    "DEX": 0,
    "Hp": 0,
    "ID": 16,
    "INT": 3,
    "MND": 2,
    "Mp": 0,
    "Name": "Veena",
    "Name_de": "Veena",
    "Name_en": "Veena",
    "Name_fr": "Veena",
    "Name_ja": "ヴィナ・ヴィエラ",
    "PIE": 0,
    "STR": "-1",
    "VIT": "-1"
  }
}