{
  "1": {
    "tw": "碧空"
  },
  "2": {
    "tw": "晴朗"
  },
  "3": {
    "tw": "陰雲"
  },
  "4": {
    "tw": "薄霧"
  },
  "5": {
    "tw": "微風"
  },
  "6": {
    "tw": "強風"
  },
  "7": {
    "tw": "小雨"
  },
  "8": {
    "tw": "暴雨"
  },
  "9": {
    "tw": "打雷"
  },
  "10": {
    "tw": "雷雨"
  },
  "11": {
    "tw": "揚沙"
  },
  "12": {
    "tw": "沙塵暴"
  },
  "13": {
    "tw": "高溫"
  },
  "14": {
    "tw": "熱浪"
  },
  "15": {
    "tw": "小雪"
  },
  "16": {
    "tw": "暴雪"
  },
  "17": {
    "tw": "妖霧"
  },
  "18": {
    "tw": "極光"
  },
  "19": {
    "tw": "黑暗"
  },
  "20": {
    "tw": "絕命"
  },
  "21": {
    "tw": "陰雲"
  },
  "22": {
    "tw": "雷雲"
  },
  "23": {
    "tw": "暴風雨"
  },
  "24": {
    "tw": "暴風雨"
  },
  "25": {
    "tw": "陰沉"
  },
  "26": {
    "tw": "熱浪"
  },
  "27": {
    "tw": "妖霧"
  },
  "28": {
    "tw": "暴風"
  },
  "29": {
    "tw": "煙霧"
  },
  "30": {
    "tw": "晴朗"
  },
  "31": {
    "tw": "晴朗"
  },
  "32": {
    "tw": "晴朗"
  },
  "33": {
    "tw": "晴朗"
  },
  "34": {
    "tw": "晴朗"
  },
  "35": {
    "tw": "極光"
  },
  "36": {
    "tw": "輝核"
  },
  "37": {
    "tw": "輝核"
  },
  "38": {
    "tw": "輝核"
  },
  "39": {
    "tw": "輝核"
  },
  "40": {
    "tw": "灘雲"
  },
  "41": {
    "tw": "灘雲"
  },
  "42": {
    "tw": "灘雲"
  },
  "43": {
    "tw": "灘雲"
  },
  "44": {
    "tw": "神意"
  },
  "45": {
    "tw": "神意"
  },
  "46": {
    "tw": "神意"
  },
  "47": {
    "tw": "神意"
  },
  "48": {
    "tw": "神意"
  },
  "49": {
    "tw": "靈風"
  },
  "50": {
    "tw": "靈電"
  },
  "51": {
    "tw": "煙武"
  },
  "52": {
    "tw": "晴朗"
  },
  "53": {
    "tw": "獸雷"
  },
  "54": {
    "tw": "雷波"
  },
  "55": {
    "tw": "獸雷"
  },
  "56": {
    "tw": "神意"
  },
  "57": {
    "tw": "打雷"
  },
  "58": {
    "tw": "打雷"
  },
  "60": {
    "tw": "神秘"
  },
  "61": {
    "tw": "神秘"
  },
  "62": {
    "tw": "小雨"
  },
  "63": {
    "tw": "晴朗"
  },
  "64": {
    "tw": "小雨"
  },
  "65": {
    "tw": "晴朗"
  },
  "66": {
    "tw": "邪天"
  },
  "67": {
    "tw": "邪天"
  },
  "68": {
    "tw": "晴朗"
  },
  "69": {
    "tw": "平衡"
  },
  "70": {
    "tw": "平衡"
  },
  "71": {
    "tw": "時光"
  },
  "72": {
    "tw": "時光"
  },
  "73": {
    "tw": "時光"
  },
  "74": {
    "tw": "鬼氣"
  },
  "75": {
    "tw": "鬼氣"
  },
  "76": {
    "tw": "鬼氣"
  },
  "77": {
    "tw": "次元"
  },
  "78": {
    "tw": "次元"
  },
  "79": {
    "tw": "次元"
  },
  "80": {
    "tw": "豪雨"
  },
  "81": {
    "tw": "豪雨"
  },
  "82": {
    "tw": "極樂"
  },
  "83": {
    "tw": "極樂"
  },
  "84": {
    "tw": "龍威"
  },
  "85": {
    "tw": "龍威"
  },
  "86": {
    "tw": "豪雨"
  },
  "87": {
    "tw": "迅雷"
  },
  "88": {
    "tw": "打雷"
  },
  "89": {
    "tw": "次元"
  },
  "90": {
    "tw": "晴朗"
  },
  "91": {
    "tw": "碧空"
  },
  "92": {
    "tw": "白旋風"
  },
  "93": {
    "tw": "白旋風"
  },
  "94": {
    "tw": "白旋風"
  },
  "95": {
    "tw": "幻想"
  },
  "96": {
    "tw": "白旋風"
  },
  "97": {
    "tw": "月夜"
  },
  "98": {
    "tw": "月夜"
  },
  "99": {
    "tw": "月夜"
  },
  "100": {
    "tw": "月夜"
  },
  "101": {
    "tw": "紅月下"
  },
  "102": {
    "tw": "朱炎"
  },
  "103": {
    "tw": "朱炎"
  },
  "104": {
    "tw": "朱炎"
  },
  "105": {
    "tw": "晴朗"
  },
  "106": {
    "tw": "晴朗"
  },
  "107": {
    "tw": "晴朗"
  },
  "108": {
    "tw": "晴朗"
  },
  "109": {
    "tw": "烈焰"
  },
  "110": {
    "tw": "海嘯"
  },
  "111": {
    "tw": "龍捲風"
  },
  "112": {
    "tw": "地震"
  },
  "113": {
    "tw": "青空"
  },
  "114": {
    "tw": "青空"
  },
  "115": {
    "tw": "青空"
  },
  "116": {
    "tw": "亂靈流"
  },
  "117": {
    "tw": "青空"
  },
  "118": {
    "tw": "無盡光"
  },
  "119": {
    "tw": "暴風"
  },
  "120": {
    "tw": "末日"
  },
  "121": {
    "tw": "末日"
  },
  "122": {
    "tw": "妖夢"
  },
  "123": {
    "tw": "妖夢"
  },
  "124": {
    "tw": "妖夢"
  },
  "125": {
    "tw": "光天"
  },
  "126": {
    "tw": "光天"
  },
  "127": {
    "tw": "末日"
  },
  "128": {
    "tw": "末日"
  },
  "129": {
    "tw": "無盡光"
  },
  "130": {
    "tw": "煙霧"
  },
  "131": {
    "tw": "末日"
  },
  "132": {
    "tw": "晴朗"
  },
  "133": {
    "tw": "靈烈火"
  },
  "134": {
    "tw": "靈飄塵"
  },
  "135": {
    "tw": "靈飛電"
  },
  "136": {
    "tw": "靈罡風"
  },
  "137": {
    "tw": "流星雨"
  },
  "138": {
    "tw": "記憶亂流"
  },
  "139": {
    "tw": "陰雲"
  },
  "140": {
    "tw": "陰雲"
  },
  "141": {
    "tw": "極光"
  },
  "142": {
    "tw": "極光"
  },
  "143": {
    "tw": "雷雲"
  },
  "144": {
    "tw": "火風暴"
  },
  "145": {
    "tw": "幻海流"
  },
  "147": {
    "tw": "決戰"
  },
  "148": {
    "tw": "月塵"
  },
  "149": {
    "tw": "磁暴"
  },
  "150": {
    "tw": "末日"
  },
  "151": {
    "tw": "星靈"
  },
  "152": {
    "tw": "星靈"
  },
  "153": {
    "tw": "星靈"
  },
  "154": {
    "tw": "星靈"
  },
  "155": {
    "tw": "星靈"
  },
  "156": {
    "tw": "虛擬"
  },
  "157": {
    "tw": "萬魔殿"
  },
  "158": {
    "tw": "萬魔殿"
  },
  "159": {
    "tw": "萬魔殿"
  },
  "160": {
    "tw": "終極"
  },
  "161": {
    "tw": "絕望"
  },
  "162": {
    "tw": "神域"
  },
  "163": {
    "tw": "神域"
  },
  "164": {
    "tw": "神域"
  },
  "165": {
    "tw": "神域"
  },
  "166": {
    "tw": "神域"
  },
  "167": {
    "tw": "神域"
  },
  "168": {
    "tw": "神域"
  },
  "169": {
    "tw": "神域"
  },
  "170": {
    "tw": "邪天"
  },
  "171": {
    "tw": "虛無"
  },
  "172": {
    "tw": "虛無"
  },
  "173": {
    "tw": "虛無"
  },
  "174": {
    "tw": "次元"
  },
  "175": {
    "tw": "次元"
  },
  "176": {
    "tw": "次元"
  },
  "177": {
    "tw": "萬魔殿"
  },
  "178": {
    "tw": "萬魔殿"
  },
  "179": {
    "tw": "詩想"
  },
  "180": {
    "tw": "虛無"
  },
  "181": {
    "tw": "閾限"
  },
  "182": {
    "tw": "閾限"
  },
  "183": {
    "tw": "虛擬"
  },
  "184": {
    "tw": "虛擬"
  },
  "185": {
    "tw": "虛擬"
  },
  "186": {
    "tw": "虛擬"
  },
  "187": {
    "tw": "記憶"
  },
  "188": {
    "tw": "戰雲"
  }
}
